uvrs/__init__.py
uvrs/__main__.py
uvrs-0.8.0.dist-info/WHEEL
uvrs-0.8.0.dist-info/entry_points.txt
uvrs-0.8.0.dist-info/METADATA
uvrs-0.8.0.dist-info/RECORD
