Metadata-Version: 2.3
Name: uvrs
Version: 0.8.0
Summary: Create and run uv scripts with POSIX standardized shebang line
License: MIT License
Requires-Dist: rich>=13.9.0
Requires-Dist: tomlkit>=0.13.3
Requires-Python: >=3.10
Project-URL: homepage, https://github.com/treyhunner/uvrs
Project-URL: issues, https://github.com/treyhunner/uvrs/issues
Project-URL: repository, https://github.com/treyhunner/uvrs
